gease/__init__.py
gease/_version.py
gease/constants.py
gease/contributors.py
gease/exceptions.py
gease/main.py
gease/orgs.py
gease/release.py
gease/repo.py
gease/rest.py
gease/uritemplate.py
gease/utils.py
gease-0.0.11.dist-info/LICENSE
gease-0.0.11.dist-info/METADATA
gease-0.0.11.dist-info/WHEEL
gease-0.0.11.dist-info/entry_points.txt
gease-0.0.11.dist-info/top_level.txt
gease-0.0.11.dist-info/RECORD
