Metadata-Version: 2.1
Name: gease
Version: 0.0.11
Summary: simply makes a git release using github api v3
Home-page: https://github.com/moremoban/gease
Author: C. W.
Author-email: wangc_2011@hotmail.com
License: MIT
Download-URL: https://github.com/moremoban/gease/archive/0.0.11.tar.gz
Keywords: python
Platform: UNKNOWN
Classifier: Topic :: Software Development :: Libraries
Classifier: Programming Language :: Python
Classifier: Intended Audience :: Developers
Classifier: Programming Language :: Python :: 2.6
Classifier: Programming Language :: Python :: 2.7
Classifier: Programming Language :: Python :: 3.3
Classifier: Programming Language :: Python :: 3.4
Classifier: Programming Language :: Python :: 3.5
Classifier: Programming Language :: Python :: 3.6
Classifier: Programming Language :: Python :: 3.7
Classifier: Programming Language :: Python :: 3.8
Requires-Dist: crayons
Requires-Dist: requests
